android_bp-0.3.0.dist-info/METADATA
android_bp-0.3.0.dist-info/WHEEL
android_bp/__init__.py
android_bp/android_bp.cpython-311-darwin.so
android_bp-0.3.0.dist-info/RECORD
