Metadata-Version: 2.3
Name: android_bp
Version: 0.3.0
Classifier: Programming Language :: Rust
Classifier: Programming Language :: Python :: Implementation :: CPython
Classifier: Programming Language :: Python :: Implementation :: PyPy
Summary: A python module to parse Android.bp files
Keywords: android,bp,parser,blueprint,soong
Home-Page: https://github.com/tardyp/rs-bp
Author: tardyp
License: MIT
Requires-Python: >=3.8
Project-URL: Source Code, https://github.com/tardyp/rs-bp
